{
    "basicStats": "Estatísticas Básicas",
    "ascensionMaterials": "Materiais de Ascensão",
    "bestWeapon": "Melhor Arma",
    "refinement": "Refinamento",
    "otherWeapons": "Outras Armas",
    "degree": "°",
    "bestArtifacts": "Melhor Conjunto de Artefatos",
    "effect" : "Efeito",
    "onePiece": "1 Peça",
    "twoPieces": "2 Peças",
    "fourPieces": "4 Peças",
    "artifactsPieces": "Peças dos Artefatos",
    "artifactsMainStats": "Status Principais dos Artefatos",
    "sands": "Ampulheta",
    "goblet": "Cálice",
    "circlet": "Tiara",
    "artifactsSubStats": "Sub-Status dos Artefatos",
    "otherArtifacts": "Outros Conjuntos de Artefatos",
    "talentPriority": "Prioridade de Talentos",
    "bestTeams": "Melhores Times",
    "bestTeam": "Melhor Time",
    "mainDps": "Main DPS",
    "subDps": "Sub-DPS",
    "support": "Suporte",
    "ascensionCosts": "Custo de Ascensão",
    "talentCosts": "Custo de Talentos",
    "cost": "Custo",
    "lvl": "Nv",
    "level": "Nível",
    "recommendedCharacters": "Personagens Recomendados",
    "story": "História",
    "talents": "Talentos",
    "passives": "Passivas",
    "passive": "Passiva",
    "constellations": "Constelações",
    "basicHp": "Vida Básica",
    "basicAttack": "Ataque Básico",
    "basicDefense": "Defesa Básica",
    "atk": "ATQ",
    "hp": "Vida",
    "statsIconDescription": "Ícone representando",
    "hpPercent": "Vida %",
    "elementalMastery": "Proficiência Elemental",
    "atkPercent": "ATQ %",
    "atkPercentOrEnergyRecharge": "ATQ % / Recarga de Energia",
    "energyRechargeOrElementalMastery": "Recarga % / Proficiência",
    "atkPercentOrElementalMastery": "ATQ % / Proficiência",
    "defPercent": "DEF %",
    "critRate": "Taxa Crítica",
    "critDamage": "Dano Crítico",
    "critRateOrElementalMastery": "Taxa Crítica / Proficiência",
    "energyRecharge": "Recarga de Energia",
    "critRateOrDamage": "Taxa Crítica / Dano Crítico",
    "healingBonus": "Bônus de Cura",
    "anemoBonus": "Bônus de Dano Anemo",
    "geoBonus": "Bônus de Dano Geo",
    "electroBonus": "Bônus de Dano Electro",
    "dendroBonus": "Bônus de Dano Dendro",
    "hydroBonus": "Bônus de Dano Hydro",
    "pyroBonus": "Bônus de Dano Pyro",
    "cryoBonus": "Bônus de Dano Cryo",
    "elementalSkill": "Habilidade Elemental",
    "elementalBurst": "Supremo",
    "normalAttack": "Ataque Normal",
    "rightClick": "Botão Direito",
    "weaponList": "Lista de Armas",
    "sword": "Espada",
    "claymore": "Espadão",
    "bow": "Arco",
    "catalyst": "Catalisador",
    "polearm": "Lança",
    "stars": "Estrelas",
    "star": "Estrela",
    "allA": "Todas",
    "allB": "Todos",
    "search": "Pesquise",
    "rarity": "Raridade",
    "weaponType": "Tipo de Arma",
    "element": "Elemento",
    "charactersList": "Lista de Personagens",
    "artifactsList": "Lista de Artefatos"
}
  